{"_type":"export","__export_format":4,"__export_date":"2020-05-17T06:55:48.073Z","__export_source":"insomnia.desktop.app:v7.1.1","resources":[{"_id":"req_735b3fd7e4904d2b8ba0d224900255b8","authentication":{},"body":{"mimeType":"application/json","text":"{\n\t\"username\":\"joe200\",\n\t\"password\":\"abc123\",\n\t\"department\":\"books\",\n\t\"role\":\"normal\"\n}"},"created":1589090791500,"description":"","headers":[{"id":"pair_28803c7d6e7a4cf9a8fefd959c27b47d","name":"Content-Type","value":"application/json"}],"isPrivate":false,"metaSortKey":-1588838031676,"method":"POST","modified":1589694138866,"name":"Register a normal user POST /api/register","parameters":[],"parentId":"wrk_a27e8cbbe92543cab247b5f6edc37b05","settingDisableRenderRequestBody":false,"settingEncodeUrl":true,"settingFollowRedirects":"global","settingRebuildPath":true,"settingSendCookies":true,"settingStoreCookies":true,"url":"localhost:5000/api/register","_type":"request"},{"_id":"wrk_a27e8cbbe92543cab247b5f6edc37b05","created":1589090791483,"description":"","modified":1589090791483,"name":"NODE-AUTH2-PROJECT","parentId":null,"_type":"workspace"},{"_id":"req_5eb80c2409504be7bc04e2ca4004939b","authentication":{},"body":{"mimeType":"application/json","text":"{\n\t\"username\":\"joe100\",\n\t\"password\":\"abc123\",\n\t\"department\":\"books\",\n\t\"role\":\"admin\"\n}"},"created":1589693603246,"description":"","headers":[{"id":"pair_28803c7d6e7a4cf9a8fefd959c27b47d","name":"Content-Type","value":"application/json"}],"isPrivate":false,"metaSortKey":-1588837967927,"method":"POST","modified":1589694144377,"name":"Register an admin user POST /api/register","parameters":[],"parentId":"wrk_a27e8cbbe92543cab247b5f6edc37b05","settingDisableRenderRequestBody":false,"settingEncodeUrl":true,"settingFollowRedirects":"global","settingRebuildPath":true,"settingSendCookies":true,"settingStoreCookies":true,"url":"localhost:5000/api/register","_type":"request"},{"_id":"req_e0a2c37227ec4b92a0d7b99f6ca123fa","authentication":{"disabled":false,"password":"abc123","type":"basic","username":"joe4"},"body":{"mimeType":"application/json","text":"{\n\t\"username\":\"joe300\",\n\t\"password\":\"abc123\"\n}"},"created":1589091572501,"description":"","headers":[{"id":"pair_b8114c62d55d48a68b2b77a6abe5c2e6","name":"Content-Type","value":"application/json"}],"isPrivate":false,"metaSortKey":-1588837583372.75,"method":"POST","modified":1589694037082,"name":"Login (invalid credentials) POST /api/login","parameters":[],"parentId":"wrk_a27e8cbbe92543cab247b5f6edc37b05","settingDisableRenderRequestBody":false,"settingEncodeUrl":true,"settingFollowRedirects":"global","settingRebuildPath":true,"settingSendCookies":true,"settingStoreCookies":true,"url":"localhost:5000/api/login","_type":"request"},{"_id":"req_c64f3e14bd644323a9b282aad6bd2511","authentication":{"disabled":false,"password":"abc123","type":"basic","username":"joe4"},"body":{"mimeType":"application/json","text":"{\n\t\"username\":\"joe100\",\n\t\"password\":\"abc123\",\n\t\"department\":\"books\",\n\t\"role\":\"admin\"\n}"},"created":1589091564637,"description":"","headers":[{"id":"pair_b8114c62d55d48a68b2b77a6abe5c2e6","name":"Content-Type","value":"application/json"}],"isPrivate":false,"metaSortKey":-1588837262567.5,"method":"POST","modified":1589694166771,"name":"Login (valid credentials)  POST /api/login","parameters":[],"parentId":"wrk_a27e8cbbe92543cab247b5f6edc37b05","settingDisableRenderRequestBody":false,"settingEncodeUrl":true,"settingFollowRedirects":"global","settingRebuildPath":true,"settingSendCookies":true,"settingStoreCookies":true,"url":"localhost:5000/api/login","_type":"request"},{"_id":"req_efa73ac6e8794439ab4af2f461ad270b","authentication":{"disabled":false,"password":"abc123","type":"basic","username":"joe100"},"body":{},"created":1589090791494,"description":"","headers":[],"isPrivate":false,"metaSortKey":-1588836620957,"method":"GET","modified":1589110459696,"name":"Get Users GET /api/users","parameters":[],"parentId":"wrk_a27e8cbbe92543cab247b5f6edc37b05","settingDisableRenderRequestBody":false,"settingEncodeUrl":true,"settingFollowRedirects":"global","settingRebuildPath":true,"settingSendCookies":true,"settingStoreCookies":true,"url":"localhost:5000/api/users","_type":"request"},{"_id":"req_7163e64085b14c51bd99ce7931e0f986","authentication":{},"body":{},"created":1589097665255,"description":"","headers":[],"isPrivate":false,"metaSortKey":-1588836620932,"method":"GET","modified":1589102020551,"name":"Logout","parameters":[],"parentId":"wrk_a27e8cbbe92543cab247b5f6edc37b05","settingDisableRenderRequestBody":false,"settingEncodeUrl":true,"settingFollowRedirects":"global","settingRebuildPath":true,"settingSendCookies":true,"settingStoreCookies":true,"url":"localhost:5000/api/logout","_type":"request"},{"_id":"req_f0ca0bbf03ae457ab0485f093f525732","authentication":{},"body":{},"created":1589099960260,"description":"","headers":[],"isPrivate":false,"metaSortKey":-1588836620907,"method":"DELETE","modified":1589110244349,"name":"Delete user","parameters":[],"parentId":"wrk_a27e8cbbe92543cab247b5f6edc37b05","settingDisableRenderRequestBody":false,"settingEncodeUrl":true,"settingFollowRedirects":"global","settingRebuildPath":true,"settingSendCookies":true,"settingStoreCookies":true,"url":"localhost:5000/api/delete/5","_type":"request"},{"_id":"env_e285409266d34a2cba1c9663e6b4fc4f","color":null,"created":1589090791487,"data":{},"dataPropertyOrder":null,"isPrivate":false,"metaSortKey":1588836608736,"modified":1589090791487,"name":"Base Environment","parentId":"wrk_a27e8cbbe92543cab247b5f6edc37b05","_type":"environment"},{"_id":"jar_a41676509bc440a281a67b3d758774c8","cookies":[{"creation":"2020-05-10T11:41:19.967Z","domain":"localhost","hostOnly":true,"id":"5079068756480527","key":"token","lastAccessed":"2020-05-17T03:46:00.473Z","path":"/","value":"eyJhbGciOiJIUzI1NiIsInR5cCI6IkpXVCJ9.eyJ1c2VySWQiOjEsInVzZXJSb2xlIjoiYWRtaW4iLCJpYXQiOjE1ODk2ODcxNjB9.bDTNoC6IoSmFccB1nOmc3lMpNzY4vjFgtghDNuR3vQg"}],"created":1589090791490,"modified":1589687160473,"name":"Default Jar","parentId":"wrk_a27e8cbbe92543cab247b5f6edc37b05","_type":"cookie_jar"}]}